upgraded_railway.v
module adaptive_railway (
    input clk,
    input reset,
    input sensor_A,
    input sensor_B,
    output reg gate,
    output reg signal
);

reg [2:0] state, next_state;
reg [3:0] timer;

parameter IDLE = 3'd0,
          APPROACH = 3'd1,
          PASSING = 3'd2,
          SAFETY_WAIT = 3'd3,
          CLEAR = 3'd4;

// State register
always @(posedge clk or posedge reset) begin
    if(reset)
        state <= IDLE;
    else
        state <= next_state;
end

// Timer logic
always @(posedge clk) begin
    if(state == SAFETY_WAIT)
        timer <= timer + 1;
    else
        timer <= 0;
end

// Next-state logic
always @(*) begin
    case(state)

        IDLE:
            next_state = sensor_A ? APPROACH : IDLE;

        APPROACH:
            next_state = PASSING;

        PASSING:
            next_state = sensor_B ? SAFETY_WAIT : PASSING;

        SAFETY_WAIT:
            next_state = (timer > 5) ? CLEAR : SAFETY_WAIT;

        CLEAR:
            next_state = IDLE;

        default:
            next_state = IDLE;
    endcase
end

// Output logic
always @(*) begin
    case(state)

        IDLE, CLEAR: begin
            gate = 0;
            signal = 0;
        end

        APPROACH, PASSING, SAFETY_WAIT: begin
            gate = 1;
            signal = 1;
        end
    endcase
end

endmodule

upgraded_tb.v
module adaptive_tb;

reg clk = 0;
reg reset;
reg sensor_A;
reg sensor_B;

wire gate;
wire signal;

adaptive_railway uut (
    .clk(clk),
    .reset(reset),
    .sensor_A(sensor_A),
    .sensor_B(sensor_B),
    .gate(gate),
    .signal(signal)
);

// clock generation
always #5 clk = ~clk;

initial begin
    $dumpfile("adaptive.vcd");
    $dumpvars(0, adaptive_tb);

    reset = 1;
    sensor_A = 0;
    sensor_B = 0;

    #10 reset = 0;

    // Train approaches
    #20 sensor_A = 1;

    // Train passes
    #20 sensor_A = 0;
    sensor_B = 1;

    #20 sensor_B = 0;

    #200 $finish;
end

endmodule

adaptive.vcd
$date
	Thu Feb 12 23:01:19 2026
$end
$version
	Icarus Verilog
$end
$timescale
	1s
$end
$scope module adaptive_tb $end
$var wire 1 ! signal $end
$var wire 1 " gate $end
$var reg 1 # clk $end
$var reg 1 $ reset $end
$var reg 1 % sensor_A $end
$var reg 1 & sensor_B $end
$scope module uut $end
$var wire 1 # clk $end
$var wire 1 $ reset $end
$var wire 1 % sensor_A $end
$var wire 1 & sensor_B $end
$var reg 1 " gate $end
$var reg 3 ' next_state [2:0] $end
$var reg 1 ! signal $end
$var reg 3 ( state [2:0] $end
$var reg 4 ) timer [3:0] $end
$upscope $end
$upscope $end
$enddefinitions $end
#0
$dumpvars
bx )
b0 (
b0 '
0&
0%
1$
0#
0"
0!
$end
#5
b0 )
1#
#10
0#
0$
#15
1#
#20
0#
#25
1#
#30
b1 '
0#
1%
#35
1!
1"
b10 '
b1 (
1#
#40
0#
#45
b10 (
1#
#50
b11 '
0#
1&
0%
#55
b11 (
1#
#60
0#
#65
b1 )
1#
#70
0#
0&
#75
b10 )
1#
#80
0#
#85
b11 )
1#
#90
0#
#95
b100 )
1#
#100
0#
#105
b101 )
1#
#110
0#
#115
b100 '
b110 )
1#
#120
0#
#125
0!
0"
b0 '
b111 )
b100 (
1#
#130
0#
#135
b0 )
b0 (
1#
